biopytk/.gitignore
biopytk/__init__.py
biopytk/_version.py
biopytk/aa_seq.py
biopytk/bio_seq.py
biopytk/fasta_tk.py
biopytk/main.py
biopytk/sequenceBuilder.py
biopytk/structs.py
biopytk/test.py
biopytk/__pycache__/aa_seq.cpython-311.pyc
biopytk/__pycache__/bio_seq.cpython-311.pyc
biopytk/__pycache__/dnaToolkit.cpython-311.pyc
biopytk/__pycache__/fasta_tk.cpython-311.pyc
biopytk/__pycache__/geneticConst.cpython-311.pyc
biopytk/__pycache__/sequenceBuilder.cpython-311.pyc
biopytk/__pycache__/structs.cpython-311.pyc
biopytk-0.2.2.dist-info/LICENSE
biopytk-0.2.2.dist-info/METADATA
biopytk-0.2.2.dist-info/WHEEL
biopytk-0.2.2.dist-info/top_level.txt
biopytk-0.2.2.dist-info/RECORD
