Metadata-Version: 2.1
Name: biopytk
Version: 0.2.2
Summary: Personal Toolkit for Bioinformatics and Computational Biology pipelines. (WIP)
Author-email: Stephen Cheney <scheney.cb@gmail.com>
Project-URL: Homepage, https://github.com/Steve-Cheney/biopytk
Classifier: Programming Language :: Python :: 3
Classifier: License :: OSI Approved :: MIT License
Classifier: Operating System :: OS Independent
Requires-Python: >=3.11
License-File: LICENSE
Requires-Dist: importlib-metadata ; python_version < "3.8"
